flatten_imports/__init__.py
flatten_imports-0.1.0.dist-info/LICENSE
flatten_imports-0.1.0.dist-info/METADATA
flatten_imports-0.1.0.dist-info/WHEEL
flatten_imports-0.1.0.dist-info/entry_points.txt
flatten_imports-0.1.0.dist-info/RECORD
