Metadata-Version: 2.1
Name: flatten-imports
Version: 0.1.0
Summary: 
Author: Willem Thiart
Author-email: himself@willemthiart.com
Requires-Python: >=3.11,<4.0
Classifier: Programming Language :: Python :: 3
Classifier: Programming Language :: Python :: 3.11
Requires-Dist: libcst (>=1.5.0,<2.0.0)
